taskman/__init__.py
taskman/cli.py
taskman/core.py
taskman/jj.py
taskman/migrate.py
taskman/server.py
taskman/skills/jj/SKILL.md
taskman/skills/jj/patterns/gotchas.md
taskman/skills/jj/patterns/workflows.md
taskman/skills/jj/reference/commands.md
taskman/skills/jj/reference/config.md
taskman/skills/jj/reference/conflicts.md
taskman/skills/jj/reference/git-interop.md
taskman/skills/jj/reference/revsets.md
taskman/skills/taskman/SKILL.md
taskman/skills/taskman/compact.md
taskman/skills/taskman/complete.md
taskman/skills/taskman/continue.md
taskman/skills/taskman/describe.md
taskman/skills/taskman/handoff.md
taskman/skills/taskman/history-batch.md
taskman/skills/taskman/history-diffs.md
taskman/skills/taskman/history-search.md
taskman/skills/taskman/remember.md
taskman/skills/taskman/sync.md
taskman/skills/taskman/wt.md
taskmanager_exe-0.4.8.dist-info/METADATA
taskmanager_exe-0.4.8.dist-info/WHEEL
taskmanager_exe-0.4.8.dist-info/entry_points.txt
taskmanager_exe-0.4.8.dist-info/licenses/LICENSE
taskmanager_exe-0.4.8.dist-info/RECORD
