Metadata-Version: 2.4
Name: taskmanager-exe
Version: 0.4.8
Summary: Version-controlled task management for AI agents
License-File: LICENSE
Requires-Python: >=3.11
Requires-Dist: mcp
Provides-Extra: dev
Requires-Dist: pytest>=8.0; extra == 'dev'
